pretix_autocart/__init__.py
pretix_autocart/apps.py
pretix_autocart/signals.py
pretix_autocart/urls.py
pretix_autocart/views.py
pretix_autocart/locale/django.pot
pretix_autocart/locale/de/LC_MESSAGES/django.mo
pretix_autocart/locale/de/LC_MESSAGES/django.po
pretix_autocart/locale/de_Informal/.gitkeep
pretix_autocart/locale/de_Informal/LC_MESSAGES/django.mo
pretix_autocart/locale/de_Informal/LC_MESSAGES/django.po
pretix_autocart/static/pretix_autocart/.gitkeep
pretix_autocart/static/pretix_autocart/script.js
pretix_autocart/static/pretix_autocart/crypto-js/LICENSE.txt
pretix_autocart/static/pretix_autocart/crypto-js/crypto-js.min.js
pretix_autocart/static/pretix_autocart/jsencrypt/LICENSE.txt
pretix_autocart/static/pretix_autocart/jsencrypt/jsencrypt.min.js
pretix_autocart/static/pretix_autocart/jsencrypt/jsencrypt.min.js.LICENSE.txt
pretix_autocart/templates/pretix_autocart/.gitkeep
pretix_autocart-1.0.20251228.0.dist-info/licenses/LICENSE
pretix_autocart-1.0.20251228.0.dist-info/METADATA
pretix_autocart-1.0.20251228.0.dist-info/WHEEL
pretix_autocart-1.0.20251228.0.dist-info/entry_points.txt
pretix_autocart-1.0.20251228.0.dist-info/top_level.txt
pretix_autocart-1.0.20251228.0.dist-info/RECORD
