Metadata-Version: 2.4
Name: pretix-autocart
Version: 1.0.20251228.0
Summary: Enables autocompletition of pretix's carts and questions using the URL's fragment
Author-email: Furizon Team <webservice@furizon.net>, Luca Sorace <public.stranck@gmail.com>
Maintainer-email: Furizon Team <webservice@furizon.net>, Luca Sorace <public.stranck@gmail.com>
License: Apache
Project-URL: homepage, https://github.com/orgs/APSfurizon/pretix-autocart
Project-URL: repository, https://github.com/orgs/APSfurizon/pretix-autocart
Keywords: pretix
License-File: LICENSE
Dynamic: license-file
